LICENSE
README.md
pyproject.toml
dxpq/__init__.py
dxpq/connection.py
dxpq/cursor.py
dxpq.egg-info/PKG-INFO
dxpq.egg-info/SOURCES.txt
dxpq.egg-info/dependency_links.txt
dxpq.egg-info/requires.txt
dxpq.egg-info/top_level.txt
tests/test_connection.py
tests/test_cursor.py