Metadata-Version: 2.4
Name: dxpq
Version: 0.0.7
Summary: A Python wrapper for PostgreSQL interaction using a C extension
Author-email: Pedro Barbosa <pedrohsbarbosa99@gmail.com>
Project-URL: Homepage, https://github.com/pedrohsbarbosa99/dxpq
Classifier: Programming Language :: Python :: 3
Classifier: License :: OSI Approved :: MIT License
Classifier: Operating System :: OS Independent
Requires-Python: >=3.6
License-File: LICENSE
Requires-Dist: dxpq_ext==0.0.2
Dynamic: license-file
